pytest_assume/__init__.py
pytest_assume/hooks.py
pytest_assume/plugin.py
pytest_assume-2.4.3.dist-info/LICENSE.txt
pytest_assume-2.4.3.dist-info/METADATA
pytest_assume-2.4.3.dist-info/WHEEL
pytest_assume-2.4.3.dist-info/entry_points.txt
pytest_assume-2.4.3.dist-info/top_level.txt
pytest_assume-2.4.3.dist-info/RECORD
